lazybids_ui/.env
lazybids_ui/__init__.py
lazybids_ui/main.py
lazybids_ui/src/__init__.py
lazybids_ui/src/html_api.py
lazybids_ui/src/models.py
lazybids_ui/src/random_image.py
lazybids_ui/src/rest_api.py
lazybids_ui/src/worker.py
lazybids_ui/static/ac0b1d72-515f-45d7-8f5c-ac6d86326bc8Screenshot 2024-10-23 112122.png
lazybids_ui/static/bars.svg
lazybids_ui/static/empty.html
lazybids_ui/static/mermaid_dark.css
lazybids_ui/static/mermaid_dark2.css
lazybids_ui/static/niivue/index.js
lazybids_ui/static/niivue.umd.js
lazybids_ui/templates/components/create_dataset.html
lazybids_ui/templates/components/dataset_card.html
lazybids_ui/templates/components/dataset_header.html
lazybids_ui/templates/components/dataset_view.html
lazybids_ui/templates/components/datasets.html
lazybids_ui/templates/components/edit_dataset.html
lazybids_ui/templates/components/error.html
lazybids_ui/templates/components/header.html
lazybids_ui/templates/components/redirect_home.html
lazybids_ui/templates/components/scans.html
lazybids_ui/templates/components/session_view.html
lazybids_ui/templates/components/subject_view.html
lazybids_ui/templates/components/table.html
lazybids_ui/templates/root.html
lazybids_ui-0.0.2.dist-info/LICENSE
lazybids_ui-0.0.2.dist-info/METADATA
lazybids_ui-0.0.2.dist-info/WHEEL
lazybids_ui-0.0.2.dist-info/entry_points.txt
lazybids_ui-0.0.2.dist-info/RECORD
