Metadata-Version: 2.1
Name: lazybids-ui
Version: 0.0.2
Summary: A web-based graphical user interface server for viewing (and manipulating) BIDS datasets, build on lazybids.
Author: Roelant
Author-email: roelanteijgelaar@hotmail.com
Requires-Python: >=3.10,<3.12
Classifier: Programming Language :: Python :: 3
Classifier: Programming Language :: Python :: 3.10
Classifier: Programming Language :: Python :: 3.11
Requires-Dist: fastapi[all] (>=0.111.0,<0.112.0)
Requires-Dist: lazybids (>=0.2.1,<0.3.0)
Requires-Dist: openneuro-py (>=2023.1.0,<2024.0.0)
Requires-Dist: pillow (>=10.4.0,<11.0.0)
Requires-Dist: pretty-html-table (>=0.9.16,<0.10.0)
Requires-Dist: py7zr (>=0.21.0,<0.22.0)
Requires-Dist: pydantic (>=2.7.4,<3.0.0)
Requires-Dist: pytailwindcss-extra (>=0.1.0,<0.2.0)
Requires-Dist: scalar-fastapi (>=1.0.3,<2.0.0)
Requires-Dist: sqlmodel (>=0.0.19,<0.0.20)
